{
    "id": "6c40ee09-225e-4eb2-9403-e5724c5190f9",
    "title": "Silvanus of Nevrast",
    "slug": "silvanus-of-nevrast-myth",
    "state": "public",
    "isWip": true,
    "isDraft": true,
    "entityClass": "Myth",
    "icon": "fa-solid fa-file",
    "url": "http://www.worldanvil.com/w/arteria-adorath/a/silvanus-of-nevrast-myth",
    "subscribergroups": [],
    "folderId": "-1",
    "tags": "",
    "updateDate": {
        "date": "2021-11-03 22:58:39.000000",
        "timezone_type": 3,
        "timezone": "UTC"
    },
    "position": null,
    "excerpt": null,
    "template": "myth",
    "wordcount": 16,
    "creationDate": {
        "date": "2021-11-03 22:58:39.000000",
        "timezone_type": 3,
        "timezone": "UTC"
    },
    "publicationDate": null,
    "notificationDate": null,
    "likes": null,
    "views": null,
    "metadata_user": null,
    "metadata_article": null,
    "css_classes": null,
    "cssStyles": null,
    "passcode": null,
    "author": {
        "id": "8059089b-cf59-45b1-b328-a9efcd36f47b",
        "title": "adorath",
        "slug": null,
        "state": null,
        "isWip": null,
        "isDraft": null,
        "entityClass": "User",
        "icon": "fa-solid fa-user",
        "url": "http://www.worldanvil.com/author/adorath",
        "subscribergroups": [],
        "folderId": null,
        "tags": null,
        "updateDate": null
    },
    "category": {
        "id": "3ec0822b-07a8-4437-bf5f-ae11258387f1",
        "title": "Nevrast",
        "slug": "nevrast-category",
        "url": "http://www.worldanvil.com/w/arteria-adorath/c/nevrast-category"
    },
    "world": {
        "id": "238a9dbc-1c3f-4f72-838f-336a90f6c31c",
        "title": "Arteria",
        "slug": "arteria-adorath",
        "state": "public",
        "isWip": null,
        "isDraft": null,
        "entityClass": "World",
        "icon": "fa-solid fa-globe-stand",
        "url": "http://www.worldanvil.com/w/arteria-adorath",
        "subscribergroups": [],
        "folderId": "-1",
        "tags": "",
        "updateDate": {
            "date": "2024-03-29 03:20:43.000000",
            "timezone_type": 3,
            "timezone": "UTC"
        }
    },
    "cover": {
        "id": 1952401,
        "title": "Arteria world cover",
        "slug": null,
        "state": "public",
        "isWip": null,
        "isDraft": null,
        "entityClass": "Image",
        "icon": "fa-solid fa-image",
        "url": "https://www.worldanvil.com/uploads/images/6c977e75d750e89b02a0040abf994163.jpg",
        "subscribergroups": [],
        "folderId": null,
        "tags": "",
        "updateDate": {
            "date": "2021-02-07 07:25:04.000000",
            "timezone_type": 3,
            "timezone": "UTC"
        }
    },
    "content": "Guarding the island of Nevrast, Silvanus is a looming presence",
    "contentParsed": "Guarding the island of Nevrast, Silvanus is a looming presence",
    "sections": {
        "displaySidebar": {
            "title": "",
            "position": "",
            "content": true,
            "contentParsed": "1"
        },
        "folderId": {
            "title": "",
            "position": "",
            "content": "-1",
            "contentParsed": "-1"
        }
    },
    "relations": {
        "childrenArticles": {
            "title": "",
            "position": "sidebar",
            "type": "collection"
        },
        "memories": {
            "title": "",
            "position": "sidebar",
            "type": "collection"
        },
        "manuscripts": {
            "title": "",
            "position": "sidebar",
            "type": "collection"
        },
        "documents": {
            "title": "",
            "position": "sidebar",
            "type": "collection"
        },
        "ethnicities": {
            "title": "",
            "position": "sidebar",
            "type": "collection"
        },
        "species": {
            "title": "",
            "position": "sidebar",
            "type": "collection"
        },
        "locations": {
            "title": "",
            "position": "sidebar",
            "type": "collection"
        },
        "people": {
            "title": "",
            "position": "sidebar",
            "type": "collection"
        },
        "organizations": {
            "title": "",
            "position": "sidebar",
            "type": "collection"
        },
        "items": {
            "title": "",
            "position": "sidebar",
            "type": "collection"
        },
        "vehicles": {
            "title": "",
            "position": "sidebar",
            "type": "collection"
        }
    }
}